vectorwrap/__init__.py
vectorwrap/clickhouse_backend.py
vectorwrap/duckdb_backend.py
vectorwrap/mariadb_backend.py
vectorwrap/mysql_backend.py
vectorwrap/pg_backend.py
vectorwrap/redis_backend.py
vectorwrap/rethinkdb_backend.py
vectorwrap/sqlite_backend.py
vectorwrap/integrations/__init__.py
vectorwrap/integrations/appwrite.py
vectorwrap/integrations/langchain.py
vectorwrap/integrations/llamaindex.py
vectorwrap/integrations/milvus.py
vectorwrap/integrations/qdrant.py
vectorwrap/integrations/supabase.py
vectorwrap-0.8.0.dist-info/licenses/LICENSE
vectorwrap-0.8.0.dist-info/METADATA
vectorwrap-0.8.0.dist-info/WHEEL
vectorwrap-0.8.0.dist-info/top_level.txt
vectorwrap-0.8.0.dist-info/RECORD
