Metadata-Version: 2.4
Name: vectorwrap
Version: 0.8.0
Summary: Universal vector search wrapper for Postgres, MySQL, MariaDB, SQLite, DuckDB, ClickHouse, Redis, RethinkDB (pgvector, HeatWave, sqlite-vss, DuckDB VSS, ClickHouse ANN, RediSearch, Real-time changefeeds)
Author-email: Mihir Ahuja <mihir@example.com>
License-Expression: MIT
Project-URL: Homepage, https://github.com/mihirahuja/vectorwrap
Project-URL: Repository, https://github.com/mihirahuja/vectorwrap
Project-URL: Issues, https://github.com/mihirahuja/vectorwrap/issues
Keywords: vector,database,embeddings,similarity,search,postgresql,mysql,mariadb,sqlite,duckdb,clickhouse,redis
Classifier: Development Status :: 3 - Alpha
Classifier: Intended Audience :: Developers
Classifier: Programming Language :: Python :: 3
Classifier: Programming Language :: Python :: 3.10
Classifier: Programming Language :: Python :: 3.11
Classifier: Programming Language :: Python :: 3.12
Classifier: Topic :: Database
Classifier: Topic :: Scientific/Engineering :: Artificial Intelligence
Requires-Python: >=3.10
License-File: LICENSE
Requires-Dist: psycopg[binary]>=3.1
Requires-Dist: mysql-connector-python>=8.3
Requires-Dist: numpy>=1.26
Requires-Dist: typing-extensions>=4.5.0
Provides-Extra: sqlite
Requires-Dist: pysqlite3>=0.5.0; extra == "sqlite"
Requires-Dist: sqlite-vss>=0.1.2; extra == "sqlite"
Provides-Extra: duckdb
Requires-Dist: duckdb>=0.10.2; extra == "duckdb"
Provides-Extra: clickhouse
Requires-Dist: clickhouse-connect>=0.6.0; extra == "clickhouse"
Provides-Extra: redis
Requires-Dist: redis[hiredis]>=5.0.0; extra == "redis"
Provides-Extra: rethinkdb
Requires-Dist: rethinkdb>=2.4.0; extra == "rethinkdb"
Requires-Dist: hnswlib>=0.7.0; extra == "rethinkdb"
Provides-Extra: langchain
Requires-Dist: langchain>=0.1.0; extra == "langchain"
Provides-Extra: llamaindex
Requires-Dist: llama-index>=0.10.0; extra == "llamaindex"
Provides-Extra: milvus
Requires-Dist: pymilvus>=2.3.0; extra == "milvus"
Provides-Extra: qdrant
Requires-Dist: qdrant-client>=1.7.0; extra == "qdrant"
Provides-Extra: dev
Requires-Dist: pytest>=6.0; extra == "dev"
Requires-Dist: pytest-cov>=4.0; extra == "dev"
Requires-Dist: black>=23.0; extra == "dev"
Requires-Dist: ruff>=0.1.0; extra == "dev"
Requires-Dist: mypy>=1.0; extra == "dev"
Requires-Dist: pre-commit>=3.0; extra == "dev"
Provides-Extra: all
Requires-Dist: vectorwrap[clickhouse,duckdb,langchain,llamaindex,milvus,qdrant,redis,rethinkdb,sqlite]; extra == "all"
Provides-Extra: integrations
Requires-Dist: vectorwrap[langchain,llamaindex,milvus,qdrant]; extra == "integrations"
Provides-Extra: test
Requires-Dist: vectorwrap[clickhouse,dev,duckdb,redis,rethinkdb,sqlite]; extra == "test"
Dynamic: license-file
